multi_party_schnorr.cp36-win_amd64.pyd
multi_party_schnorr-0.1.9.dist-info/LICENSE
multi_party_schnorr-0.1.9.dist-info/METADATA
multi_party_schnorr-0.1.9.dist-info/WHEEL
multi_party_schnorr-0.1.9.dist-info/top_level.txt
multi_party_schnorr-0.1.9.dist-info/RECORD
