Metadata-Version: 2.1
Name: multi-party-schnorr
Version: 0.1.9
Summary: UNKNOWN
Home-page: https://github.com/namuyan/multi-party-schnorr
License: GPL-3
Platform: UNKNOWN
Classifier: License :: OSI Approved :: GNU General Public License v3 (GPLv3)
Classifier: Programming Language :: Python :: 3
Classifier: Programming Language :: Rust
Requires-Python: >=3.5
